LICENSE
README.md
setup.py
redbot_orm/__init__.py
redbot_orm/__main__.py
redbot_orm/cli.py
redbot_orm/common.py
redbot_orm/errors.py
redbot_orm/postgres.py
redbot_orm/registry.py
redbot_orm/scaffold.py
redbot_orm/sqlite.py
redbot_orm/version.py
redbot_orm.egg-info/PKG-INFO
redbot_orm.egg-info/SOURCES.txt
redbot_orm.egg-info/dependency_links.txt
redbot_orm.egg-info/entry_points.txt
redbot_orm.egg-info/requires.txt
redbot_orm.egg-info/top_level.txt