Metadata-Version: 2.1
Name: redbot-orm
Version: 1.0.2
Summary: Postgres and SQLite extensions for Red-DiscordBot
Home-page: https://github.com/vertyco/redbot-orm
Author: Vertyco
Author-email: alex.c.goble@gmail.com
Project-URL: Homepage, https://github.com/vertyco/redbot-orm
Project-URL: Bug Tracker, https://github.com/vertyco/redbot-orm/issues
Project-URL: Changelog, https://github.com/vertyco/redbot-orm/blob/main/CHANGELOG.md
Keywords: postgres,sqlite,piccolo,red,redbot,red-discordbot,red,bot,discord,database,async,asyncpg,aiosqlite,orm
Classifier: Development Status :: 5 - Production/Stable
Classifier: License :: OSI Approved :: MIT License
Classifier: Intended Audience :: Developers
Classifier: Operating System :: OS Independent
Classifier: Natural Language :: English
Classifier: Programming Language :: Python :: 3.10
Classifier: Programming Language :: Python :: 3.11
Classifier: Programming Language :: Python :: 3.12
Classifier: Framework :: Pydantic :: 2
Classifier: Topic :: Internet
Classifier: Topic :: Software Development :: Libraries
Classifier: Topic :: Software Development :: Libraries :: Python Modules
Classifier: Topic :: Utilities
Classifier: Typing :: Typed
Requires-Python: >=3.10
License-File: LICENSE
